MANIFEST.in
README.md
setup.py
django_bootstrap_typeahead/__init__.py
django_bootstrap_typeahead/fields.py
django_bootstrap_typeahead/widgets.py
django_bootstrap_typeahead.egg-info/PKG-INFO
django_bootstrap_typeahead.egg-info/SOURCES.txt
django_bootstrap_typeahead.egg-info/dependency_links.txt
django_bootstrap_typeahead.egg-info/not-zip-safe
django_bootstrap_typeahead.egg-info/top_level.txt
django_bootstrap_typeahead/static/css/bootstrap-typeahead.css
django_bootstrap_typeahead/static/js/bootstrap-typeahead.js
django_bootstrap_typeahead/static/js/bootstrap3-typeahead.min.js