Metadata-Version: 1.0
Name: django-bootstrap-typeahead
Version: 1.1.5
Summary: Convert django model choice fields into typeahead fields.
Home-page: http://thegoods.aj7may.com/django-bootstrap-typeahead
Author: A.J. May
Author-email: aj7may@gmail.com
License: MIT License
Keywords: django bootstrap typeahead form widget input
Platform: UNKNOWN
